staticsg/__init__.py
staticsg/roman_ssg_util.py
staticsg/romanssg.py
staticsg_rrezinkin-1.0.5.dist-info/LICENSE
staticsg_rrezinkin-1.0.5.dist-info/METADATA
staticsg_rrezinkin-1.0.5.dist-info/WHEEL
staticsg_rrezinkin-1.0.5.dist-info/top_level.txt
staticsg_rrezinkin-1.0.5.dist-info/RECORD
