Metadata-Version: 2.1
Name: staticsg-rrezinkin
Version: 1.0.5
Summary: This is a simple Static Site Generator
Home-page: https://github.com/roman-rezinkin/RomanStaticSG
Author: Roman Rezinkin
Author-email: roman.rezinkin@hotmail.com
License: UNKNOWN
Project-URL: Bug Tracker, https://github.com/roman-rezinkin/RomanStaticSG/issues
Platform: UNKNOWN
Classifier: Programming Language :: Python :: 3
Classifier: License :: OSI Approved :: MIT License
Classifier: Operating System :: OS Independent
Requires-Python: >=3.6
License-File: LICENSE
